__init__.py
__main__.py
cli.py
unleashed_py.py
unleashed-py/__init__.py
unleashed-py/__main__.py
unleashed-py/cli.py
unleashed-py/unleashed_py.py
unleashed_py-1.0.8.dist-info/LICENSE
unleashed_py-1.0.8.dist-info/METADATA
unleashed_py-1.0.8.dist-info/WHEEL
unleashed_py-1.0.8.dist-info/top_level.txt
unleashed_py-1.0.8.dist-info/RECORD
