Metadata-Version: 2.1
Name: unleashed-py
Version: 1.0.8
Summary: Python package to connect to the Unleashed Software inventory management API
Home-page: https://github.com/jonathanStrange0/unleashed-py
Author: Jonathan Mucha
Author-email: jonmucha@gmail.com
License: MIT
Platform: UNKNOWN
Classifier: Development Status :: 2 - Pre-Alpha
Classifier: License :: OSI Approved :: MIT License
Classifier: Programming Language :: Python
Classifier: Programming Language :: Python :: 3.6
Classifier: Programming Language :: Python :: 3.7
Requires-Python: >=3.6
Requires-Dist: requests
